AUTHORS
COPYING
MANIFEST.in
README.rst
setup.py
django_reportapi.egg-info/PKG-INFO
django_reportapi.egg-info/SOURCES.txt
django_reportapi.egg-info/dependency_links.txt
django_reportapi.egg-info/not-zip-safe
django_reportapi.egg-info/requires.txt
django_reportapi.egg-info/top_level.txt
docs/Makefile
docs/conf.py
docs/contents.txt
docs/glossary.txt
docs/index.txt
docs/make.bat
docs/_build/doctrees/ru/contents.doctree
docs/_build/doctrees/ru/environment.pickle
docs/_build/doctrees/ru/glossary.doctree
docs/_build/doctrees/ru/index.doctree
docs/_build/doctrees/ru/ref/api.doctree
docs/_build/doctrees/ru/ref/conf.doctree
docs/_build/doctrees/ru/ref/exceptions.doctree
docs/_build/doctrees/ru/ref/filters.doctree
docs/_build/doctrees/ru/ref/index.doctree
docs/_build/doctrees/ru/ref/managers.doctree
docs/_build/doctrees/ru/ref/models.doctree
docs/_build/doctrees/ru/ref/routers.doctree
docs/_build/doctrees/ru/ref/sites.doctree
docs/_build/doctrees/ru/ref/templatetags.doctree
docs/_build/doctrees/ru/ref/utils.doctree
docs/_build/doctrees/ru/ref/views.doctree
docs/_build/doctrees/ru/releases/3.0.doctree
docs/_build/doctrees/ru/releases/3.1.doctree
docs/_build/doctrees/ru/releases/index.doctree
docs/_build/html/ru/.buildinfo
docs/_build/html/ru/contents.html
docs/_build/html/ru/genindex.html
docs/_build/html/ru/glossary.html
docs/_build/html/ru/index.html
docs/_build/html/ru/objects.inv
docs/_build/html/ru/py-modindex.html
docs/_build/html/ru/search.html
docs/_build/html/ru/searchindex.js
docs/_build/html/ru/_modules/index.html
docs/_build/html/ru/_modules/reportapi/exceptions.html
docs/_build/html/ru/_sources/contents.txt
docs/_build/html/ru/_sources/glossary.txt
docs/_build/html/ru/_sources/index.txt
docs/_build/html/ru/_sources/ref/api.txt
docs/_build/html/ru/_sources/ref/conf.txt
docs/_build/html/ru/_sources/ref/exceptions.txt
docs/_build/html/ru/_sources/ref/filters.txt
docs/_build/html/ru/_sources/ref/index.txt
docs/_build/html/ru/_sources/ref/managers.txt
docs/_build/html/ru/_sources/ref/models.txt
docs/_build/html/ru/_sources/ref/routers.txt
docs/_build/html/ru/_sources/ref/sites.txt
docs/_build/html/ru/_sources/ref/templatetags.txt
docs/_build/html/ru/_sources/ref/utils.txt
